imaxt_image/__init__.py
imaxt_image/_version.py
imaxt_image/datasets/__init__.py
imaxt_image/datasets/stpt.py
imaxt_image/display/__init__.py
imaxt_image/display/scaling.py
imaxt_image/external/__init__.py
imaxt_image/external/tifffile.py
imaxt_image/image/__init__.py
imaxt_image/image/display.py
imaxt_image/image/metadata.py
imaxt_image/image/omexmlmetadata.py
imaxt_image/image/scaling.py
imaxt_image/image/tiffimage.py
imaxt_image/io/__init__.py
imaxt_image/io/dax.py
imaxt_image/io/metadata.py
imaxt_image/io/omexmlmetadata.py
imaxt_image/io/tiffimage.py
imaxt_image/merfish/__init__.py
imaxt_image/merfish/display.py
imaxt_image/misc/__init__.py
imaxt_image/misc/bytescale.py
imaxt_image/registration/__init__.py
imaxt_image/registration/cross_correlation.py
imaxt_image/registration/minimization.py
imaxt_image/registration/mutual_information.py
imaxt_image/registration/utils.py
imaxt_image/viewer/__init__.py
imaxt_image/viewer/stpt.py
imaxt_image-0.16.5.dist-info/AUTHORS.rst
imaxt_image-0.16.5.dist-info/METADATA
imaxt_image-0.16.5.dist-info/WHEEL
imaxt_image-0.16.5.dist-info/top_level.txt
imaxt_image-0.16.5.dist-info/RECORD
